commugen_api/__init__.py
commugen_api/commugen_api.py
commugen_api/response_objects.py
commugen_api-0.7.dist-info/METADATA
commugen_api-0.7.dist-info/WHEEL
commugen_api-0.7.dist-info/top_level.txt
commugen_api-0.7.dist-info/RECORD
