Metadata-Version: 2.1
Name: commugen-api
Version: 0.7
Summary: Python wrapper for commugen api
Home-page: https://bitbucket.org/kobi_commugen/commugen_api/
Author: kobi kolodner
Author-email: kobi@commugen.com
License: MIT
Classifier: Development Status :: 2 - Pre-Alpha
Requires-Dist: requests
Requires-Dist: tablib
Requires-Dist: curlify
Requires-Dist: keyring
